MANIFEST.in
README.md
requirements-min-django.txt
requirements-test.txt
requirements.txt
setup.py
database_deadlock/__init__.py
database_deadlock/admin.py
database_deadlock/apps.py
database_deadlock/models.py
database_deadlock/migrations/0001_initial.py
database_deadlock/migrations/0002_auto_20190513_1337.py
database_deadlock/migrations/__init__.py
database_deadlock/sql/deadlock.postgresql.sql
database_deadlock/sql/deadlock.sqlite3.sql
database_deadlock/tests/__init__.py
database_deadlock/tests/manage.py
database_deadlock/tests/models.py
database_deadlock/tests/settings.py
database_deadlock/tests/tests.py
database_deadlock/tests/urls.py
database_deadlock/tests/views.py
database_deadlock/tests/management/__init__.py
database_deadlock/tests/management/commands/__init__.py
django_deadlock.egg-info/PKG-INFO
django_deadlock.egg-info/SOURCES.txt
django_deadlock.egg-info/dependency_links.txt
django_deadlock.egg-info/requires.txt
django_deadlock.egg-info/top_level.txt